test/__init__.py
triton_sushang/__init__.py
triton_sushang/client.py
triton_sushang-0.1.0.dist-info/LICENSE
triton_sushang-0.1.0.dist-info/METADATA
triton_sushang-0.1.0.dist-info/WHEEL
triton_sushang-0.1.0.dist-info/top_level.txt
triton_sushang-0.1.0.dist-info/RECORD
